{
 "accept_payment": 0,
 "allow_comments": 0,
 "allow_delete": 0,
 "allow_edit": 0,
 "allow_incomplete": 0,
 "allow_multiple": 0,
 "allow_print": 0,
 "amount": 0.0,
 "amount_based_on_field": 0,
 "apply_document_permissions": 0,
 "button_label": "Save",
 "creation": "2021-02-11 13:11:11.835748",
 "currency": "SAR",
 "doc_type": "Enroll Workshops",
 "docstatus": 0,
 "doctype": "Web Form",
 "idx": 0,
 "is_standard": 1,
 "login_required": 0,
 "max_attachment_size": 0,
 "modified": "2021-02-11 13:12:22.005917",
 "modified_by": "Administrator",
 "module": "Wadeem",
 "name": "workshop-schedule",
 "owner": "Administrator",
 "payment_button_label": "Buy Now",
 "published": 1,
 "route": "schedule",
 "route_to_success_link": 0,
 "show_attachments": 0,
 "show_in_grid": 0,
 "show_sidebar": 0,
 "sidebar_items": [],
 "success_url": "/workshop-schedule",
 "title": "Workshop Schedule",
 "web_form_fields": [
  {
   "allow_read_on_all_link_options": 0,
   "fieldname": "naming_series",
   "fieldtype": "Select",
   "hidden": 0,
   "label": "Enroll Workshop ID",
   "max_length": 0,
   "max_value": 0,
   "options": "W-",
   "read_only": 0,
   "reqd": 0,
   "show_in_filter": 0
  },
  {
   "allow_read_on_all_link_options": 0,
   "fieldname": "workshop_id",
   "fieldtype": "Table",
   "hidden": 0,
   "label": "Workshop",
   "max_length": 0,
   "max_value": 0,
   "options": "Workshop",
   "read_only": 0,
   "reqd": 0,
   "show_in_filter": 0
  }
 ]
}